curlpy.py
curlpy-0.1.0.dist-info/LICENSE
curlpy-0.1.0.dist-info/WHEEL
curlpy-0.1.0.dist-info/METADATA
curlpy-0.1.0.dist-info/RECORD
