Metadata-Version: 2.1
Name: curlpy
Version: 0.1.0
Summary: curl like python interface
License: MIT
Author: ucpr
Author-email: contact@ucpr.dev
Requires-Python: >=3.8,<4.0
Classifier: License :: OSI Approved :: MIT License
Classifier: Programming Language :: Python :: 3
Classifier: Programming Language :: Python :: 3.8
